pydggsapi/__init__.py
pydggsapi/api.py
pydggsapi/dependencies/api/collection_providers.py
pydggsapi/dependencies/api/collections.py
pydggsapi/dependencies/api/dggrs.py
pydggsapi/dependencies/api/mercator.py
pydggsapi/dependencies/collections_providers/abstract_collection_provider.py
pydggsapi/dependencies/collections_providers/clickhouse_collection_provider.py
pydggsapi/dependencies/collections_providers/parquet_collection_provider.py
pydggsapi/dependencies/collections_providers/zarr_collection_provider.py
pydggsapi/dependencies/dggrs_providers/abstract_dggrs_provider.py
pydggsapi/dependencies/dggrs_providers/h3_dggrs_provider.py
pydggsapi/dependencies/dggrs_providers/igeo7_dggrs_provider.py
pydggsapi/main.py
pydggsapi/models/ogc_dggs/core.py
pydggsapi/models/ogc_dggs/data_retrieval.py
pydggsapi/models/ogc_dggs/tags
pydggsapi/models/ogc_dggs/zone_query.py
pydggsapi/models/tiles_model.py
pydggsapi/request_example.py
pydggsapi/routers/dggs_api.py
pydggsapi/routers/tiles_api.py
pydggsapi/schemas/.gitkeep
pydggsapi/schemas/api/collection_providers.py
pydggsapi/schemas/api/collections.py
pydggsapi/schemas/api/dggrs_providers.py
pydggsapi/schemas/authentication.py
pydggsapi/schemas/common_geojson.py
pydggsapi/schemas/ogc_collections/collections.py
pydggsapi/schemas/ogc_collections/extent.py
pydggsapi/schemas/ogc_dggs/common_ogc_dggs_api.py
pydggsapi/schemas/ogc_dggs/dggrs_descrption.py
pydggsapi/schemas/ogc_dggs/dggrs_list.py
pydggsapi/schemas/ogc_dggs/dggrs_zones.py
pydggsapi/schemas/ogc_dggs/dggrs_zones_data.py
pydggsapi/schemas/ogc_dggs/dggrs_zones_info.py
pydggsapi/schemas/tiles/tiles.py
pydggsapi/test/empty.json
pydggsapi/test/tags
pydggsapi/test/test_collection_provider/collection_provider_test_collection_data-retrieval_query_zone_data.py
pydggsapi/test/test_collection_provider/collection_provider_test_collection_data-retrieval_query_zone_data_H3.py
pydggsapi/test/test_core_dggrs_description.py
pydggsapi/test/test_core_dggrs_list.py
pydggsapi-0.1.5.dist-info/METADATA
pydggsapi-0.1.5.dist-info/WHEEL
pydggsapi-0.1.5.dist-info/entry_points.txt
pydggsapi-0.1.5.dist-info/licenses/LICENSE
pydggsapi-0.1.5.dist-info/RECORD
