Metadata-Version: 2.4
Name: pydggsapi
Version: 0.1.5
Summary: A python FastAPI OGC DGGS API implementation
License-Expression: Apache-2.0
License-File: LICENSE
Author: Wai Tik Chan
Author-email: wai.tik.chan@ut.ee
Maintainer: Wai Tik Chan
Maintainer-email: wai.tik.chan@ut.ee
Requires-Python: >=3.10,<3.13
Classifier: Programming Language :: Python :: 3
Classifier: Programming Language :: Python :: 3.10
Classifier: Programming Language :: Python :: 3.11
Classifier: Programming Language :: Python :: 3.12
Requires-Dist: clickhouse-cityhash (>=1.0.2.4,<2.0.0.0)
Requires-Dist: clickhouse-driver[lz4,zstd] (>=0.2.6,<0.3.0)
Requires-Dist: dggrid4py (>=0.4.1,<0.5.0)
Requires-Dist: duckdb (>=1.3.2,<2.0.0)
Requires-Dist: fastapi (>=0.115.6,<0.116.0)
Requires-Dist: gunicorn (>=23.0.0,<24.0.0)
Requires-Dist: h3 (>=4.2.0,<5.0.0)
Requires-Dist: mapbox-vector-tile (>=2.0.1,<3.0.0)
Requires-Dist: morecantile (>=5.0.0,<6.0.0)
Requires-Dist: nest-asyncio (>=1.6.0,<2.0.0)
Requires-Dist: pyproj (>=3.6.1,<4.0.0)
Requires-Dist: pytest (>=8.3.4,<9.0.0)
Requires-Dist: python-dotenv (>=1.0.0,<2.0.0)
Requires-Dist: scipy (>=1.15.0,<2.0.0)
Requires-Dist: shapely (>=2.0.2,<3.0.0)
Requires-Dist: tinydb (>=4.8.2,<5.0.0)
Requires-Dist: uvicorn (>=0.23.2,<0.24.0)
Requires-Dist: xarray[io] (>=2025.3.1,<2026.0.0)
